{"cameraMode":{"drawMode":0,"name":"Shaded","section":"Shading Mode"},"sceneLighting":true,"audioPlay":false,"sceneViewState":{"showFog":true,"showMaterialUpdate":false,"showSkybox":true,"showFlares":true,"showImageEffects":true,"showParticleSystems":true},"in2DMode":false,"pivot":{"x":10.362257957458496,"y":4.879118919372559,"z":-3.7749266624450685},"rotation":{"x":0.13796404004096986,"y":-0.498104065656662,"z":0.08066757023334503,"w":0.8522887825965881},"size":1.0496243238449097,"orthographic":false}